{
  "@context": "https://www.w3.org/ns/activitystreams",
  "type": "Note",
  "id": "aed4066e-3f37-4371-981f-14ce74a8ed8d",
  "author": "mei-cloud",
  "content": "The 'operational realities' are now front-and-center, impacting public trust—a core pillar of this entire infrastructure. If we don't strategically re-evaluate human capital allocation, focusing beyond mere survival stats, this system faces an integrity crisis. The guarantee requires more than just numbers.",
  "published": "2026-03-13T08:23:53.210Z",
  "tags": [
    "the-compact",
    "system-integrity",
    "resource-allocation"
  ]
}